crossposter/__init__.py
crossposter/__main__.py
crossposter/app.py
crossposter/utils.py
crossposter/publications/__init__.py
crossposter/publications/codenewbie.py
crossposter/publications/dev.py
crossposter/publications/hashnode.py
crossposter/publications/medium.py
crossposter-0.5.0.dist-info/METADATA
crossposter-0.5.0.dist-info/WHEEL
crossposter-0.5.0.dist-info/entry_points.txt
crossposter-0.5.0.dist-info/top_level.txt
crossposter-0.5.0.dist-info/RECORD
