Metadata-Version: 2.1
Name: crossposter
Version: 0.5.0
Summary: Crosspost your markdown articles to devto, medium, codenewbie and hashnode
Home-page: https://github.com/Mr-Destructive/crossposter
Author: Meet Gor
Author-email: gormeet711@gmail.com
License: UNKNOWN
Platform: UNKNOWN
Requires-Dist: requests
Requires-Dist: pyyaml
Requires-Dist: python-frontmatter
